bacpipe/__init__.py
bacpipe/config.yaml
bacpipe/generate_embeddings.py
bacpipe/main.py
bacpipe/settings.yaml
bacpipe/embedding_evaluation/label_embeddings.py
bacpipe/embedding_evaluation/classification/classify.py
bacpipe/embedding_evaluation/classification/evaluate_classifier.py
bacpipe/embedding_evaluation/classification/train_classifier.py
bacpipe/embedding_evaluation/clustering/cluster.py
bacpipe/embedding_evaluation/distance_evalutation/distances.py
bacpipe/embedding_evaluation/visualization/dashboard.py
bacpipe/embedding_evaluation/visualization/visualize.py
bacpipe/embedding_generation_pipelines/README.md
bacpipe/embedding_generation_pipelines/__init__.py
bacpipe/embedding_generation_pipelines/utils.py
bacpipe/embedding_generation_pipelines/dimensionality_reduction/pca.py
bacpipe/embedding_generation_pipelines/dimensionality_reduction/sparse_pca.py
bacpipe/embedding_generation_pipelines/dimensionality_reduction/t_sne.py
bacpipe/embedding_generation_pipelines/dimensionality_reduction/umap.py
bacpipe/embedding_generation_pipelines/feature_extractors/audiomae.py
bacpipe/embedding_generation_pipelines/feature_extractors/audioprotopnet.py
bacpipe/embedding_generation_pipelines/feature_extractors/aves_especies.py
bacpipe/embedding_generation_pipelines/feature_extractors/avesecho_passt.py
bacpipe/embedding_generation_pipelines/feature_extractors/beats.py
bacpipe/embedding_generation_pipelines/feature_extractors/biolingual.py
bacpipe/embedding_generation_pipelines/feature_extractors/birdaves_especies.py
bacpipe/embedding_generation_pipelines/feature_extractors/birdmae.py
bacpipe/embedding_generation_pipelines/feature_extractors/birdnet.py
bacpipe/embedding_generation_pipelines/feature_extractors/convnext_birdset.py
bacpipe/embedding_generation_pipelines/feature_extractors/google_whale.py
bacpipe/embedding_generation_pipelines/feature_extractors/hbdet.py
bacpipe/embedding_generation_pipelines/feature_extractors/insect459.py
bacpipe-1.2.0.dist-info/METADATA
bacpipe-1.2.0.dist-info/WHEEL
bacpipe-1.2.0.dist-info/licenses/LICENSE
bacpipe-1.2.0.dist-info/RECORD
