Metadata-Version: 2.4
Name: bacpipe
Version: 1.2.0
Summary: Use bacpipe to streamline the process of generating embeddings and analysing your PAM datasets.
Author-email: "Vincent S. Kather" <vkather@gmail.com>
License-File: LICENSE
Requires-Python: >=3.11
Requires-Dist: anyio==4.10.0
Requires-Dist: astunparse==1.6.3
Requires-Dist: attrs==25.3.0
Requires-Dist: audioread==3.0.1
Requires-Dist: bleach==6.2.0
Requires-Dist: bokeh==3.7.3; sys_platform == 'linux'
Requires-Dist: cachetools==5.5.2
Requires-Dist: certifi==2025.8.3
Requires-Dist: cffi==1.17.1
Requires-Dist: charset-normalizer==3.4.3
Requires-Dist: chex==0.1.90
Requires-Dist: click==8.2.1
Requires-Dist: cloudpickle==2.2.1
Requires-Dist: contextlib2==21.6.0
Requires-Dist: contourpy==1.3.3
Requires-Dist: crcmod==1.7
Requires-Dist: cycler==0.12.1
Requires-Dist: decorator==5.2.1
Requires-Dist: dill==0.3.1.1
Requires-Dist: dnspython==2.7.0
Requires-Dist: docopt==0.6.2
Requires-Dist: einops==0.8.0
Requires-Dist: etils==1.13.0
Requires-Dist: fastavro==1.12.0
Requires-Dist: fasteners==0.20
Requires-Dist: filelock==3.19.1
Requires-Dist: flatbuffers==25.2.10
Requires-Dist: flax==0.10.0
Requires-Dist: fonttools==4.59.2
Requires-Dist: fsspec==2025.9.0
Requires-Dist: gast==0.6.0
Requires-Dist: google-auth-oauthlib==1.2.2
Requires-Dist: google-auth==2.40.3
Requires-Dist: google-pasta==0.2.0
Requires-Dist: grpcio==1.65.5
Requires-Dist: h11==0.16.0
Requires-Dist: h5py==3.14.0
Requires-Dist: hdfs==2.7.3
Requires-Dist: hear21passt==0.0.26
Requires-Dist: hf-xet==1.1.9
Requires-Dist: httpcore==1.0.9
Requires-Dist: httplib2==0.22.0
Requires-Dist: httpx==0.27.0
Requires-Dist: huggingface-hub==0.34.4
Requires-Dist: humanize==4.13.0
Requires-Dist: idna==3.10
Requires-Dist: importlib-resources==6.5.2
Requires-Dist: iniconfig==2.1.0
Requires-Dist: jax==0.4.33
Requires-Dist: jaxlib==0.4.33
Requires-Dist: jinja2==3.1.6
Requires-Dist: joblib==1.5.2
Requires-Dist: jsonpickle==3.3.0
Requires-Dist: jsonschema-specifications==2025.4.1
Requires-Dist: jsonschema==4.25.1
Requires-Dist: kagglehub==0.3.13
Requires-Dist: keras==3.11.0; sys_platform == 'linux'
Requires-Dist: kiwisolver==1.4.9
Requires-Dist: lazy-loader==0.4
Requires-Dist: libclang==18.1.1
Requires-Dist: librosa==0.10.2.post1
Requires-Dist: linkify-it-py==2.0.3
Requires-Dist: llvmlite==0.44.0
Requires-Dist: markdown-it-py==4.0.0
Requires-Dist: markdown==3.9
Requires-Dist: markupsafe==3.0.2
Requires-Dist: matplotlib==3.10.6
Requires-Dist: mdit-py-plugins==0.5.0
Requires-Dist: mdurl==0.1.2
Requires-Dist: ml-collections==0.1.0
Requires-Dist: ml-dtypes==0.5.3; sys_platform == 'linux'
Requires-Dist: mpmath==1.3.0
Requires-Dist: msgpack==1.1.1
Requires-Dist: narwhals==2.3.0
Requires-Dist: nest-asyncio==1.6.0
Requires-Dist: networkx==3.5
Requires-Dist: numba==0.61.2
Requires-Dist: numpy==1.26.4
Requires-Dist: nvidia-cublas-cu12==12.4.5.8; sys_platform == 'linux'
Requires-Dist: nvidia-cuda-cupti-cu12==12.4.127; sys_platform == 'linux'
Requires-Dist: nvidia-cuda-nvrtc-cu12==12.4.127; sys_platform == 'linux'
Requires-Dist: nvidia-cuda-runtime-cu12==12.4.127; sys_platform == 'linux'
Requires-Dist: nvidia-cudnn-cu12==9.1.0.70; sys_platform == 'linux'
Requires-Dist: nvidia-cufft-cu12==11.2.1.3; sys_platform == 'linux'
Requires-Dist: nvidia-curand-cu12==10.3.5.147; sys_platform == 'linux'
Requires-Dist: nvidia-cusolver-cu12==11.6.1.9; sys_platform == 'linux'
Requires-Dist: nvidia-cusparse-cu12==12.3.1.170; sys_platform == 'linux'
Requires-Dist: nvidia-cusparselt-cu12==0.6.2; sys_platform == 'linux'
Requires-Dist: nvidia-nccl-cu12==2.21.5; sys_platform == 'linux'
Requires-Dist: nvidia-nvjitlink-cu12==12.4.127; sys_platform == 'linux'
Requires-Dist: nvidia-nvtx-cu12==12.4.127; sys_platform == 'linux'
Requires-Dist: oauthlib==3.3.1
Requires-Dist: objsize==0.7.1
Requires-Dist: opt-einsum==3.4.0
Requires-Dist: optax==0.2.3
Requires-Dist: orbax-checkpoint==0.6.4
Requires-Dist: orjson==3.10.7
Requires-Dist: packaging==25.0
Requires-Dist: pandas==2.2.3
Requires-Dist: panel==1.6.2
Requires-Dist: param==2.2.1
Requires-Dist: pillow==11.3.0
Requires-Dist: platformdirs==4.4.0
Requires-Dist: pluggy==1.6.0
Requires-Dist: pooch==1.8.2
Requires-Dist: proto-plus==1.26.1
Requires-Dist: protobuf==6.32.1; sys_platform == 'linux'
Requires-Dist: pyarrow-hotfix==0.7
Requires-Dist: pyarrow==16.1.0
Requires-Dist: pyasn1-modules==0.4.2
Requires-Dist: pyasn1==0.6.1
Requires-Dist: pycparser==2.22
Requires-Dist: pydot==1.4.2
Requires-Dist: pygments==2.19.2
Requires-Dist: pyjwt==2.10.1
Requires-Dist: pymongo==4.14.1
Requires-Dist: pynndescent==0.5.13
Requires-Dist: pyparsing==3.2.3
Requires-Dist: pytest==8.4.2
Requires-Dist: python-dateutil==2.9.0.post0
Requires-Dist: pytz==2025.2
Requires-Dist: pyyaml==6.0.2
Requires-Dist: redis==5.3.1
Requires-Dist: referencing==0.36.2
Requires-Dist: regex==2025.9.1
Requires-Dist: requests-oauthlib==2.0.0
Requires-Dist: requests==2.32.3
Requires-Dist: rich==14.1.0
Requires-Dist: rpds-py==0.27.1
Requires-Dist: rsa==4.9.1
Requires-Dist: safetensors==0.4.5
Requires-Dist: scikit-learn==1.7.1
Requires-Dist: scipy==1.13.1
Requires-Dist: seaborn==0.13.2
Requires-Dist: setuptools==80.9.0
Requires-Dist: six==1.17.0
Requires-Dist: sniffio==1.3.1
Requires-Dist: sounddevice==0.4.7
Requires-Dist: soundfile==0.12.1
Requires-Dist: soxr==0.3.7
Requires-Dist: tensorboard-data-server==0.7.2; sys_platform == 'linux'
Requires-Dist: tensorboard==2.20.0; sys_platform == 'linux'
Requires-Dist: tensorflow-hub==0.16.0; sys_platform == 'linux'
Requires-Dist: tensorflow==2.15.1; sys_platform == 'win32'
Requires-Dist: tensorflow==2.20.0; sys_platform == 'linux'
Requires-Dist: tensorstore==0.1.74; sys_platform == 'linux'
Requires-Dist: termcolor==3.1.0
Requires-Dist: threadpoolctl==3.6.0
Requires-Dist: timm==1.0.11
Requires-Dist: tokenizers==0.22.0
Requires-Dist: toolz==1.0.0
Requires-Dist: torch==2.6
Requires-Dist: torchaudio==2.6
Requires-Dist: torchvision==0.21.0
Requires-Dist: tornado==6.5.2
Requires-Dist: tqdm==4.67.1
Requires-Dist: transformers==4.56.0
Requires-Dist: triton==3.2.0; sys_platform == 'linux'
Requires-Dist: typing-extensions==4.15.0
Requires-Dist: tzdata==2025.2
Requires-Dist: uc-micro-py==1.0.3
Requires-Dist: umap-learn==0.5.9.post2
Requires-Dist: urllib3==2.5.0
Requires-Dist: uvicorn==0.23.2
Requires-Dist: uvloop==0.20.0; sys_platform == 'linux'
Requires-Dist: webencodings==0.5.1
Requires-Dist: werkzeug==3.1.3
Requires-Dist: wheel==0.45.1
Requires-Dist: wrapt==1.14.2
Requires-Dist: xyzservices==2025.4.0
Requires-Dist: zipp==3.23.0
Requires-Dist: zstandard==0.24.0
